unicat/__init__.py
unicat/api.py
unicat/asset.py
unicat/class_.py
unicat/definition.py
unicat/error.py
unicat/field.py
unicat/job.py
unicat/layout.py
unicat/metadata_field.py
unicat/module.py
unicat/module_action.py
unicat/module_log.py
unicat/project.py
unicat/projectbackup.py
unicat/projectmember.py
unicat/query.py
unicat/record.py
unicat/record_class_field.py
unicat/record_field.py
unicat/transform.py
unicat/unicat.py
unicat/user.py
unicat/utils.py
unicat/mutate/__init__.py
unicat/mutate/assets.py
unicat/mutate/classes.py
unicat/mutate/definitions.py
unicat/mutate/fields.py
unicat/mutate/modules.py
unicat/mutate/project.py
unicat/mutate/queries.py
unicat/mutate/records.py
unicat-0.7.14.dist-info/METADATA
unicat-0.7.14.dist-info/WHEEL
unicat-0.7.14.dist-info/licenses/LICENSE
unicat-0.7.14.dist-info/licenses/NOTICE
unicat-0.7.14.dist-info/RECORD
