Metadata-Version: 2.4
Name: unicat
Version: 0.7.14
Summary: Unicat client library - Unicat is a Product Information Management SaaS.
Author-email: Marc Boeren <m.boeren@guidance.nl>
License: MIT License
License-File: LICENSE
License-File: NOTICE
Classifier: License :: OSI Approved :: MIT License
Classifier: Operating System :: OS Independent
Classifier: Programming Language :: Python :: 3
Requires-Python: >=3.11
Requires-Dist: requests>=2.28
